<?xml version="1.0" encoding="UTF-8"?>
<!DOCTYPE mapper PUBLIC "-//mybatis.org//DTD Mapper 3.0//EN" "http://mybatis.org/dtd/mybatis-3-mapper.dtd">
<mapper namespace="com.qiujie.jzb.mapper.AccMapper">
  <resultMap id="BaseResultMap" type="com.qiujie.jzb.model.Acc">
    <!--@mbg.generated-->
    <!--@Table acc-->
    <result column="id" jdbcType="VARCHAR" property="id" />
    <result column="no" jdbcType="VARCHAR" property="no" />
  </resultMap>
  <sql id="Base_Column_List">
    <!--@mbg.generated-->
    id, `no`
  </sql>
  <insert id="insert" parameterType="com.qiujie.jzb.model.Acc">
    <!--@mbg.generated-->
    insert into acc (id, `no`)
    values (#{id,jdbcType=VARCHAR}, #{no,jdbcType=VARCHAR})
  </insert>
  <insert id="insertSelective" parameterType="com.qiujie.jzb.model.Acc">
    <!--@mbg.generated-->
    insert into acc
    <trim prefix="(" suffix=")" suffixOverrides=",">
      <if test="id != null">
        id,
      </if>
      <if test="no != null">
        `no`,
      </if>
    </trim>
    <trim prefix="values (" suffix=")" suffixOverrides=",">
      <if test="id != null">
        #{id,jdbcType=VARCHAR},
      </if>
      <if test="no != null">
        #{no,jdbcType=VARCHAR},
      </if>
    </trim>
  </insert>
<!--auto generated by MybatisCodeHelper on 2021-03-23-->
  <select id="findAllById" resultMap="BaseResultMap">
    select <include refid="Base_Column_List"/>
    from acc
    where id=#{id,jdbcType=VARCHAR}
  </select>
</mapper>